aero_svo_api/__init__.py
aero_svo_api/api.py
aero_svo_api/async_api.py
aero_svo_api/models.py
aero_svo_api/urls.py
aero_svo_api-0.2.0.dist-info/LICENSE
aero_svo_api-0.2.0.dist-info/METADATA
aero_svo_api-0.2.0.dist-info/WHEEL
aero_svo_api-0.2.0.dist-info/top_level.txt
aero_svo_api-0.2.0.dist-info/RECORD
