Metadata-Version: 2.1
Name: aero-svo-api
Version: 0.2.0
Summary: Unoficial api wrapper for Sheremetyevo International Airport
Author-email: Nikita Bulavinov <jktujgxtu@gmail.com>
License: MIT License
Project-URL: Homepage, https://github.com/jktujg/aero-svo-api
Project-URL: Bug Tracker, https://github.com/jktujg/aero-svo-api/issues
Project-URL: Changelog, https://github.com/jktujg/aero-svo-api/blob/main/CHANGELOG.md
Keywords: api,wrapper,airport,svo,sheremetyevo,schedule,flight
Classifier: License :: OSI Approved :: MIT License
Classifier: Operating System :: OS Independent
Classifier: Programming Language :: Python :: 3.11
Classifier: Programming Language :: Python :: 3.12
Requires-Python: >=3.11
License-File: LICENSE
Requires-Dist: aiohttp ==3.9.3
Requires-Dist: pydantic ==2.6.3
Requires-Dist: pytest ==8.3.2
Requires-Dist: pytest-asyncio ==0.23.8
Requires-Dist: tenacity ==9.0.0
Requires-Dist: requests ==2.32.3
